abstraction/__init__.py
abstraction/abstraction_support_functions.py
abstraction/discover.py
abstraction/discover_mr.py
abstraction/discover_ta.py
abstraction/main.py
abstraction/transformation.py
abstraction/utils.py
pmabstraction/__init__.py
pmabstraction/abstraction_support_functions.py
pmabstraction/discover.py
pmabstraction/discover_mr.py
pmabstraction/discover_ta.py
pmabstraction/main.py
pmabstraction/transformation.py
pmabstraction/utils.py
pmabstraction-0.1.20.dist-info/METADATA
pmabstraction-0.1.20.dist-info/WHEEL
pmabstraction-0.1.20.dist-info/top_level.txt
pmabstraction-0.1.20.dist-info/RECORD
