Metadata-Version: 2.1
Name: pmabstraction
Version: 0.1.20
Summary: Log Simplification in Process mining
Home-page: https://github.com/madhubs08/simplify.git
Author: Madhavi Shankar
Author-email: madhavi.shankar@pads.rwth-aachen.de
License: GPL 3.0
Project-URL: Source, https://github.com/madhubs08/simplify.git
Platform: UNKNOWN
Requires-Dist: pm4py (==1.3.0)
